fastfem/__init__.py
fastfem/elements/__init__.py
fastfem/elements/element.py
fastfem/elements/element2d.py
fastfem/elements/linear_simplex2d.py
fastfem/elements/linear_simplex_mesh2d.py
fastfem/elements/spectral_element2d.py
fastfem/fields/__init__.py
fastfem/fields/field.py
fastfem/fields/field_operations.py
fastfem/fields/numpy_similes.py
fastfem/fields/numpy_similes_linalg.py
fastfem/mesh/__init__.py
fastfem/mesh/fundamentals.py
fastfem/mesh/generator.py
fastfem/plotter/__init__.py
fastfem/plotter/mesh_visual.py
fastfem-0.0.1.dist-info/METADATA
fastfem-0.0.1.dist-info/WHEEL
fastfem-0.0.1.dist-info/licenses/LICENSE
fastfem-0.0.1.dist-info/RECORD
