Metadata-Version: 2.3
Name: fastfem
Version: 0.0.1
Summary: A Python package for solving PDEs with the finite element method and automatic differentiation
Project-URL: Source, https://github.com/fastfem/fastfem
Project-URL: Documentation, https://fastfem.com/
Project-URL: Changelog, https://fastfem.com/changelog
Author: Kentaro Hanson, Sacha Escudier
Author-email: Sina Atalay <dev@atalay.biz>
License: Apache-2.0
Classifier: Intended Audience :: Education
Classifier: Intended Audience :: Science/Research
Classifier: License :: OSI Approved :: Apache Software License
Classifier: Operating System :: OS Independent
Classifier: Programming Language :: Python :: 3.12
Requires-Python: <3.13,>=3.12
Requires-Dist: gmsh==4.13.1
Requires-Dist: jax==0.4.35
Requires-Dist: matplotlib==3.9.3
Requires-Dist: numpy==2.2.0
Requires-Dist: pyvista[all]==0.44.2
